{
  "project_info": {
    "project_number": "1088153729423",
    "firebase_url": "https://final-project-zhangmicha-eead7.firebaseio.com",
    "project_id": "final-project-zhangmicha-eead7",
    "storage_bucket": "final-project-zhangmicha-eead7.appspot.com"
  },
  "client": [
    {
      "client_info": {
        "mobilesdk_app_id": "1:1088153729423:android:d3c190f37d1163ae",
        "android_client_info": {
          "package_name": "edu.illinois.recordingservice"
        }
      },
      "oauth_client": [
        {
          "client_id": "1088153729423-q1lg36h33fphjmu6ukelhlqr1sqert52.apps.googleusercontent.com",
          "client_type": 1,
          "android_info": {
            "package_name": "edu.illinois.recordingservice",
            "certificate_hash": "b97a4a3e48c2090151deb9983af9c03928d2f14c"
          }
        },
        {
          "client_id": "1088153729423-ut9c2fm7d6inicn8e0irvcqvsjqdc8af.apps.googleusercontent.com",
          "client_type": 3
        }
      ],
      "api_key": [
        {
          "current_key": "AIzaSyBWuKOuWSgQPNwnHdkkElkrUfJT_Y7SPVo"
        }
      ],
      "services": {
        "analytics_service": {
          "status": 1
        },
        "appinvite_service": {
          "status": 2,
          "other_platform_oauth_client": [
            {
              "client_id": "1088153729423-ut9c2fm7d6inicn8e0irvcqvsjqdc8af.apps.googleusercontent.com",
              "client_type": 3
            }
          ]
        },
        "ads_service": {
          "status": 2
        }
      }
    }
  ],
  "configuration_version": "1"
}